reqargs/__init__.py
reqargs/reqargs.py
reqarg-1.7.dist-info/METADATA
reqarg-1.7.dist-info/WHEEL
reqarg-1.7.dist-info/top_level.txt
reqarg-1.7.dist-info/RECORD
